nivestor/__init__.py
nivestor/nivestorSer.py
nivestor-0.6.dist-info/METADATA
nivestor-0.6.dist-info/WHEEL
nivestor-0.6.dist-info/top_level.txt
nivestor-0.6.dist-info/RECORD
