Metadata-Version: 2.1
Name: nivestor
Version: 0.6
Summary: A Financial Service package
Home-page: UNKNOWN
Author: Nivestor Admin
Author-email: nivestorindia@gmail.com
License: UNKNOWN
Platform: UNKNOWN
Classifier: Programming Language :: Python :: 3.7
Classifier: License :: OSI Approved :: MIT License
Classifier: Operating System :: OS Independent
